selenium_dolphin/__init__.py
selenium_dolphin/api.py
selenium_dolphin/selenium_dolphin.py
selenium_dolphin/utils.py
selenium_dolphin-1.0.6.dist-info/LICENSE
selenium_dolphin-1.0.6.dist-info/METADATA
selenium_dolphin-1.0.6.dist-info/WHEEL
selenium_dolphin-1.0.6.dist-info/top_level.txt
selenium_dolphin-1.0.6.dist-info/RECORD
