Metadata-Version: 2.1
Name: selenium_dolphin
Version: 1.0.6
Summary: A Python module for controlling Dolphin browser profiles using Selenium/Pyppeteer. It also has a Dolphin API for creating, editing, and deleting profiles.
Home-page: https://github.com/DedInc/selenium_dolphin
Author: Maehdakvan
Author-email: visitanimation@google.com
Project-URL: Bug Tracker, https://github.com/DedInc/selenium_dolphin/issues
Classifier: Programming Language :: Python :: 3
Classifier: License :: OSI Approved :: MIT License
Classifier: Operating System :: Microsoft :: Windows
Classifier: Operating System :: POSIX :: Linux
Classifier: Operating System :: MacOS
Requires-Python: >=3.6
License-File: LICENSE
Requires-Dist: requests
Requires-Dist: selenium
Requires-Dist: pyppeteer
Requires-Dist: pywinauto
